vmam.py
vmam-1.3.0.data/scripts/vmam
vmam-1.3.0.dist-info/LICENSE.md
vmam-1.3.0.dist-info/METADATA
vmam-1.3.0.dist-info/WHEEL
vmam-1.3.0.dist-info/top_level.txt
vmam-1.3.0.dist-info/RECORD
